Echoo/__init__.py
Echoo/echoo.py
Echoo-0.0.2_2306152330.data/scripts/echoo
Echoo-0.0.2.post2306152330.dist-info/LICENSE
Echoo-0.0.2.post2306152330.dist-info/METADATA
Echoo-0.0.2.post2306152330.dist-info/WHEEL
Echoo-0.0.2.post2306152330.dist-info/top_level.txt
Echoo-0.0.2.post2306152330.dist-info/zip-safe
Echoo-0.0.2.post2306152330.dist-info/RECORD
