Metadata-Version: 2.1
Name: Echoo
Version: 0.0.2-2306152330
Summary: Let your program echo to you~
Home-page: https://github.com/Lyken17/Echoo/
Author: Ligeng Zhu
Author-email: lykensyu+github@gmail.com
License: MIT
Platform: UNKNOWN
Classifier: Programming Language :: Python :: 3
License-File: LICENSE
Requires-Dist: python-telegram-bot
